{
  "kind": "collectionType",
  "collectionName": "invites",
  "info": {
    "name": "Invite",
    "description": ""
  },
  "options": {
    "increments": true,
    "timestamps": true,
    "draftAndPublish": false
  },
  "pluginOptions": {},
  "attributes": {
    "email": {
      "type": "email",
      "required": true,
      "unique": true
    },
    "confirmed": {
      "type": "boolean",
      "default": false
    },
    "code": {
      "type": "string"
    },
    "invite_link": {
      "type": "string"
    },
    "copylink": {
      "type": "copylink"
    }
  }
}
